shps/__init__.py
shps/__main__.py
shps/block.py
shps/brick.py
shps/child.py
shps/forge.py
shps/nodes.py
shps/pascal.py
shps/plotting.py
shps/shapes.py
shps/terms.py
shps/three.py
shps/types.py
shps/bases/__init__.py
shps/curve/__init__.py
shps/curve/hermite.py
shps/frame/__init__.py
shps/frame/_patch.py
shps/frame/extrude.py
shps/frame/mesh.py
shps/frame/polygon.py
shps/frame/other/SectionLib.py
shps/frame/other/interpolate.py
shps/frame/other/iquad.py
shps/frame/other/plastic.py
shps/frame/other/quad.py
shps/frame/other/scripts.py
shps/frame/other/section_limits.py
shps/frame/shapes/__init__.py
shps/frame/shapes/aisc_imperial.py
shps/frame/shapes/girder.py
shps/frame/shapes/polygon.py
shps/frame/shapes/shape.py
shps/frame/solvers/__init__.py
shps/frame/solvers/plastic.py
shps/frame/solvers/section.py
shps/frame/solvers/torsion.py
shps/frame/solvers/twist_plate.py
shps/gauss/__init__.py
shps/gauss/__main__.py
shps/gauss/_gauss.py
shps/gauss/forge.py
shps/gauss/tanhsinh.py
shps/plane/__init__.py
shps/plane/operators.py
shps/plane/shape.py
shps/rotor/__init__.py
shps/solve/_A6.py
shps/solve/_T3.py
shps/solve/_poisson_rec.py
shps/solve/fem2D.py
shps/solve/laplace.py
shps/solve/poisson.py
shps/solve/test_heat.py
shps-0.0.29.dist-info/METADATA
shps-0.0.29.dist-info/WHEEL
shps-0.0.29.dist-info/top_level.txt
shps-0.0.29.dist-info/RECORD
